camp/__init__.py
camp/generators/__init__.py
camp/generators/base.py
camp/generators/create_agent_c.py
camp/generators/create_gen_h.py
camp/generators/create_impl_c.py
camp/generators/create_impl_h.py
camp/generators/create_mgr_c.py
camp/generators/create_sql.py
camp/generators/lib/__init__.py
camp/generators/lib/campch.py
camp/generators/lib/campch_roundtrip.py
camp/generators/lib/campsettings.py
camp/generators/lib/camputil.py
camp/tools/camp.py
anms_CAmp-2.1.0.dist-info/LICENSE
anms_CAmp-2.1.0.dist-info/METADATA
anms_CAmp-2.1.0.dist-info/WHEEL
anms_CAmp-2.1.0.dist-info/entry_points.txt
anms_CAmp-2.1.0.dist-info/top_level.txt
anms_CAmp-2.1.0.dist-info/RECORD
