Metadata-Version: 2.1
Name: anms-CAmp
Version: 2.1.0
Summary: C code generator for the Asychronous Management Protocol
Author-email: JHU/APL <dtnma-support@jhuapl.edu>
Project-URL: Homepage, https://github.com/NASA-AMMOS/anms-camp
Project-URL: Bug Tracker, https://github.com/NASA-AMMOS/anms-camp/issues
Classifier: Development Status :: 5 - Production/Stable
Classifier: License :: OSI Approved :: Apache Software License
Classifier: Programming Language :: Python :: 3
Classifier: Operating System :: OS Independent
Requires-Python: >=3.7
License-File: LICENSE
Requires-Dist: anms-ace
Requires-Dist: cbor2
Requires-Dist: configobj
Requires-Dist: xdg
Provides-Extra: docs
Requires-Dist: sphinx <6 ; extra == 'docs'
Requires-Dist: sphinx-rtd-theme ; extra == 'docs'
Requires-Dist: sphinx-argparse ; extra == 'docs'
Provides-Extra: flake8
Requires-Dist: flake8 ; extra == 'flake8'
Requires-Dist: flake8-pyproject ; extra == 'flake8'
Requires-Dist: flake8-formatter-junit-xml ; extra == 'flake8'
Provides-Extra: pylint
Requires-Dist: pylint ; extra == 'pylint'
Requires-Dist: pylint-junit ; extra == 'pylint'
Provides-Extra: test
Requires-Dist: jinja2 ; extra == 'test'
Requires-Dist: pytest ; extra == 'test'
Requires-Dist: pytest-cov ; extra == 'test'
Requires-Dist: coverage ; extra == 'test'
